virgo/__init__.py
virgo/database/__init__.py
virgo/database/index_trees.py
virgo/database/make_dtrees_table.py
virgo/formats/__init__.py
virgo/formats/gadget_snapshot.py
virgo/formats/mpa_trees.py
virgo/formats/rockstar.py
virgo/formats/soap.py
virgo/formats/subfind_gadget4.py
virgo/formats/subfind_lgadget2.py
virgo/formats/subfind_lgadget3.py
virgo/formats/subfind_pgadget3.py
virgo/formats/swift.py
virgo/formats/velociraptor.py
virgo/mpi/__init__.py
virgo/mpi/errchk.py
virgo/mpi/gather_array.py
virgo/mpi/merger_tree.py
virgo/mpi/parallel_hdf5.py
virgo/mpi/parallel_sort.py
virgo/mpi/test_parallel_hdf5.py
virgo/mpi/test_parallel_sort.py
virgo/mpi/test_util.py
virgo/mpi/util.py
virgo/sims/__init__.py
virgo/sims/coco.py
virgo/sims/eagle.py
virgo/sims/millennium.py
virgo/sims/millennium2.py
virgo/sims/mxxl.py
virgo/util/__init__.py
virgo/util/exceptions.py
virgo/util/match.py
virgo/util/partial_formatter.py
virgo/util/peano.py
virgo/util/ranges.py
virgo/util/read_binary.py
virgo/util/read_multi.py
virgodc-1.0.2.dist-info/LICENSE.md
virgodc-1.0.2.dist-info/METADATA
virgodc-1.0.2.dist-info/WHEEL
virgodc-1.0.2.dist-info/top_level.txt
virgodc-1.0.2.dist-info/RECORD
