Metadata-Version: 2.2
Name: virgodc
Version: 1.0.2
Summary: Tools for working with Virgo consortium n-body simulations.
Author-email: John Helly <j.c.helly@durham.ac.uk>
Project-URL: Homepage, https://github.com/jchelly/VirgoDC
Project-URL: Issues, https://github.com/jchelly/VirgoDC/issues
Classifier: Programming Language :: Python :: 3
Classifier: License :: OSI Approved :: GNU General Public License v3 (GPLv3)
Classifier: Operating System :: OS Independent
Requires-Python: >=3.10
License-File: LICENSE.md
Requires-Dist: h5py
Requires-Dist: numpy
Requires-Dist: mpi4py
